LICENSE.txt
MANIFEST.in
README.md
setup.cfg
setup.py
swiftype_app_search/__init__.py
swiftype_app_search/__version__.py
swiftype_app_search/client.py
swiftype_app_search/exceptions.py
swiftype_app_search/swiftype_request_session.py
swiftype_app_search.egg-info/PKG-INFO
swiftype_app_search.egg-info/SOURCES.txt
swiftype_app_search.egg-info/dependency_links.txt
swiftype_app_search.egg-info/requires.txt
swiftype_app_search.egg-info/top_level.txt