Metadata-Version: 2.1
Name: swiftype-app-search
Version: 0.6.1
Summary: A Deprecated API client for Swiftype App Search - Use new elastic-app-search package instead.
Home-page: https://github.com/swiftype/swiftype-app-search-python
Author: Swiftype
Author-email: eng@swiftype.com
License: MIT
Keywords: swiftype elastic app search api
Platform: UNKNOWN
Classifier: Development Status :: 4 - Beta
Classifier: Intended Audience :: Developers
Classifier: License :: OSI Approved :: MIT License
Classifier: Programming Language :: Python :: 2
Classifier: Programming Language :: Python :: 2.7
Classifier: Programming Language :: Python :: 3
Classifier: Programming Language :: Python :: 3.3
Classifier: Programming Language :: Python :: 3.4
Classifier: Programming Language :: Python :: 3.5
Classifier: Programming Language :: Python :: 3.6
